streamsx/eventstore/__init__.py
streamsx/eventstore/_eventstore.py
streamsx.eventstore-2.8.5.dist-info/LICENSE.txt
streamsx.eventstore-2.8.5.dist-info/METADATA
streamsx.eventstore-2.8.5.dist-info/WHEEL
streamsx.eventstore-2.8.5.dist-info/top_level.txt
streamsx.eventstore-2.8.5.dist-info/RECORD
