Metadata-Version: 2.1
Name: streamsx.eventstore
Version: 2.8.5
Summary: Event Store integration for IBM Streams
Home-page: https://github.com/IBMStreams/streamsx.eventstore
Author: IBM Streams @ github.com
Author-email: hegermar@de.ibm.com
License: Apache License - Version 2.0
Keywords: streams,ibmstreams,streaming,analytics,streaming-analytics,db2,eventstore
Platform: UNKNOWN
Classifier: Development Status :: 5 - Production/Stable
Classifier: License :: OSI Approved :: Apache Software License
Classifier: Programming Language :: Python :: 3
Classifier: Programming Language :: Python :: 3.5
Classifier: Programming Language :: Python :: 3.6
Classifier: Programming Language :: Python :: 3.7
Requires-Dist: streamsx (>=1.14.6)
Requires-Dist: streamsx.toolkits
Requires-Dist: streamsx.database (>=1.5.0)
